chatgpt_gaming_framework/__init__.py
chatgpt_gaming_framework/memory/__init__.py
chatgpt_gaming_framework/memory/redismemory.py
chatgpt_gaming_framework/models/__init__.py
chatgpt_gaming_framework/models/chatgptmodel.py
chatgpt_gaming_framework/storyteller/__init__.py
chatgpt_gaming_framework/storyteller/storyteller.py
chatgpt_gaming_framework/types/__init__.py
chatgpt_gaming_framework/types/types.py
chatgpt_gaming_framework-0.1.4.dist-info/AUTHORS.rst
chatgpt_gaming_framework-0.1.4.dist-info/LICENSE
chatgpt_gaming_framework-0.1.4.dist-info/METADATA
chatgpt_gaming_framework-0.1.4.dist-info/WHEEL
chatgpt_gaming_framework-0.1.4.dist-info/top_level.txt
chatgpt_gaming_framework-0.1.4.dist-info/RECORD
